htheatpump/__init__.py
htheatpump/__main__.py
htheatpump/__version__.py
htheatpump/aiohtheatpump.py
htheatpump/htheatpump.py
htheatpump/htparams-xxxxxx-3_0_20-273.csv
htheatpump/htparams.csv
htheatpump/htparams.py
htheatpump/httimeprog.py
htheatpump/protocol.py
htheatpump/utils.py
htheatpump/scripts/__init__.py
htheatpump/scripts/daemon.py
htheatpump/scripts/htbackup.py
htheatpump/scripts/htbackup_async.py
htheatpump/scripts/htcomplparams.py
htheatpump/scripts/htcomplparams_async.py
htheatpump/scripts/htdatetime.py
htheatpump/scripts/htdatetime_async.py
htheatpump/scripts/htfastquery.py
htheatpump/scripts/htfastquery_async.py
htheatpump/scripts/htfaultlist.py
htheatpump/scripts/htfaultlist_async.py
htheatpump/scripts/hthttp.py
htheatpump/scripts/htquery.py
htheatpump/scripts/htquery_async.py
htheatpump/scripts/htset.py
htheatpump/scripts/htset_async.py
htheatpump/scripts/htshell.py
htheatpump/scripts/htshell_async.py
htheatpump/scripts/httimeprog.py
htheatpump/scripts/httimeprog_async.py
htheatpump-1.3.2.dist-info/AUTHORS.rst
htheatpump-1.3.2.dist-info/LICENSE
htheatpump-1.3.2.dist-info/METADATA
htheatpump-1.3.2.dist-info/WHEEL
htheatpump-1.3.2.dist-info/entry_points.txt
htheatpump-1.3.2.dist-info/top_level.txt
htheatpump-1.3.2.dist-info/RECORD
