Metadata-Version: 2.1
Name: htheatpump
Version: 1.3.2
Summary: Easy-to-use Python communication module for Heliotherm heat pumps
Home-page: https://github.com/dstrigl/htheatpump
Author: Daniel Strigl
License: GNU General Public License v3
Keywords: python python3 heatpump serial protocol Heliotherm
Platform: Linux
Classifier: Development Status :: 5 - Production/Stable
Classifier: Intended Audience :: Developers
Classifier: Intended Audience :: Information Technology
Classifier: Intended Audience :: Science/Research
Classifier: Intended Audience :: Manufacturing
Classifier: License :: OSI Approved :: GNU General Public License v3 (GPLv3)
Classifier: Programming Language :: Python
Classifier: Programming Language :: Python :: 3
Classifier: Programming Language :: Python :: 3.7
Classifier: Programming Language :: Python :: 3.8
Classifier: Natural Language :: English
Classifier: Operating System :: POSIX
Classifier: Operating System :: POSIX :: Linux
Classifier: Topic :: Communications
Classifier: Topic :: Home Automation
Classifier: Topic :: Scientific/Engineering
Classifier: Topic :: Software Development :: Libraries
Classifier: Topic :: Software Development :: Libraries :: Python Modules
Classifier: Topic :: System :: Hardware :: Hardware Drivers
Classifier: Topic :: Terminals :: Serial
Requires-Dist: pyserial (==3.5)
Requires-Dist: aioserial (==1.3.0)
Provides-Extra: dev
Requires-Dist: mypy (==0.931) ; extra == 'dev'
Requires-Dist: coverage (==6.2) ; extra == 'dev'
Requires-Dist: pytest (==6.2.5) ; extra == 'dev'
Requires-Dist: pytest-asyncio (==0.16.0) ; extra == 'dev'
Requires-Dist: pytest-mypy (==0.8.1) ; extra == 'dev'
Requires-Dist: pytest-cov (==3.0.0) ; extra == 'dev'
Requires-Dist: pytest-sugar (==0.9.4) ; extra == 'dev'
Requires-Dist: flake8 (==4.0.1) ; extra == 'dev'
Requires-Dist: tox (==3.24.5) ; extra == 'dev'
Provides-Extra: doc
Requires-Dist: Sphinx (==4.3.2) ; extra == 'doc'
Requires-Dist: sphinx-rtd-theme (==1.0.0) ; extra == 'doc'
Provides-Extra: test
Requires-Dist: mypy (==0.931) ; extra == 'test'
Requires-Dist: coverage (==6.2) ; extra == 'test'
Requires-Dist: pytest (==6.2.5) ; extra == 'test'
Requires-Dist: pytest-asyncio (==0.16.0) ; extra == 'test'
Requires-Dist: pytest-mypy (==0.8.1) ; extra == 'test'
Requires-Dist: pytest-cov (==3.0.0) ; extra == 'test'
Requires-Dist: pytest-sugar (==0.9.4) ; extra == 'test'
